{
    "app_id": "c2e1a38b0be8df8a86fdf0858bd101",
    "collection_id": "c4e1a38b0b9ec7dd8180deeba770",
    "items": [],
    "name": "BLEReadValues",
    "permissions": {
        "Administrator": 15,
        "Authenticated": 15
    },
    "schema": [
        {
            "ColumnName": "item_id",
            "ColumnType": "uuid",
            "PK": true
        },
        {
            "ColumnName": "gateway_mac",
            "ColumnType": "string",
            "PK": false
        },
        {
            "ColumnName": "ble_device_mac",
            "ColumnType": "string",
            "PK": false
        },
        {
            "ColumnName": "ble_device_type",
            "ColumnType": "string",
            "PK": false
        },
        {
            "ColumnName": "read_data",
            "ColumnType": "string",
            "PK": false
        }
    ]
}